librtdpy.cpython-37m-x86_64-linux-gnu.so
librtd-0.0.3.1.dist-info/RECORD
librtd-0.0.3.1.dist-info/entry_points.txt
librtd-0.0.3.1.dist-info/METADATA
librtd-0.0.3.1.dist-info/top_level.txt
librtd-0.0.3.1.dist-info/WHEEL
librtd/__init__.py
librtd/librtd.py
