Metadata-Version: 2.1
Name: librtd
Version: 0.0.3.1
Summary: Generalized k-mer return time distribution calculation
Home-page: https://github.com/IQTLabs/librtd
Author: Benjamin D. Lee
Author-email: benjamindlee@me.com
License: UNKNOWN
Platform: UNKNOWN
Classifier: Programming Language :: Python :: 3
Classifier: License :: OSI Approved :: Apache Software License
Classifier: Operating System :: OS Independent
Classifier: Development Status :: 4 - Beta
Classifier: Intended Audience :: Science/Research
Classifier: Topic :: Scientific/Engineering :: Bio-Informatics
Requires-Dist: docopt
Requires-Dist: nimporter
